{
 "slug": "i-dont-want-to-go-to-sleep",
 "pdf_page_count": 18,
 "body_page_range": [
  1,
  14
 ],
 "mapping_offset": 4,
 "mapping_deviant": null,
 "has_no_text_folder": true,
 "no_text_file_count": 18,
 "front_matter_word_count": 360,
 "license_hint": "Creative Commons Attribution 4",
 "license_warning": false,
 "layout_ambiguous_pages": [
  1,
  4,
  5,
  7,
  8,
  11,
  12,
  13,
  14
 ],
 "cache_file": "i-dont-want-to-go-to-sleep.pdf",
 "pdf_url": "https://bookdash.org/book-source-files/?download=i-dont-want-to-go-to-sleep/ebook/en-english/i-dont-want-to-go-to-sleep_en.pdf",
 "ebook_folder": "/ebook",
 "eng_folder": "/ebook/en-english",
 "pages": [
  {
   "page_no": 1,
   "word_count": 25,
   "text": "“Goodnight, Nandi.” o g o t o s t t l e n e a w p t! n ’ o ” d I “"
  },
  {
   "page_no": 2,
   "word_count": 34,
   "text": "“That’s enough now. Goodnight, Nandi.” “ I … d o n ’ t … w a n t … t o … g o … t o … s l e e p. ”"
  },
  {
   "page_no": 3,
   "word_count": 65,
   "text": "e” p! e l s o o t og ’ t w a t o n t dn I a “ n t m o r e s u p p e A r n. o t h e r b o J o u k s t! o n e m o r e s o n g? ” “Goodnight, Nandi.” “ I w"
  },
  {
   "page_no": 4,
   "word_count": 66,
   "text": "A M A M! “... I n e e d a g l a s s o f w “ a I t D P l e a s e O e? r N. ’ T W A N T P l e a s e. ” TO GO! ” P E E L S O T “It’s time to go to sleep now. Goodnight, Nandi.”"
  },
  {
   "page_no": 5,
   "word_count": 18,
   "text": "Mama sighs: “What about an adventure? Do you want an adventure?” “ … y e s … ”"
  },
  {
   "page_no": 6,
   "word_count": 25,
   "text": "“Do you want to creep through the jungle on the trail of the fearsome hippocrocoturtleduck?” Y “ Y e s! s e!! s” Y e"
  },
  {
   "page_no": 7,
   "word_count": 68,
   "text": "! y k s e h t s s o r c a l y o f t t w a n “ I! r a t s L t o e a p f r o s m t a r F i l l m ” y t! p s o w u c k i r d e t h s t a t s"
  },
  {
   "page_no": 8,
   "word_count": 114,
   "text": "N a n d i - s i z a e d n t w a g l a “ I s s s a t u r u c r e e s b h e a m e t t e t h a r s e i n e o t b o t t o f t h e o c o e a m n! g i a n t s q u e t i d p a t o d n d A o w w i t h m e a e r e! ” t e t h r b a l l e t"
  },
  {
   "page_no": 9,
   "word_count": 105,
   "text": "s g n i w y l f r e t t u b y o f k i r s “ I p a w a e a n e l f h t t o m y s t b u i l d o f o f o r d h e t r l t o a n d z o o m o w e h t l l a e e l l s ” w h e r e I ’! t i n i g n h i y t v e r a n d e"
  },
  {
   "page_no": 10,
   "word_count": 42,
   "text": "“Look here, Nandi. Here is your very own adventure boat. It’s waiting to take you wherever you want to go. See, put your head here... that’s right... and I’ll just tuck you in... there we go... now, off you go! Adventure awaits...”"
  },
  {
   "page_no": 11,
   "word_count": 2,
   "text": "“Goodnight, Nandi.”"
  },
  {
   "page_no": 12,
   "word_count": 4,
   "text": "Draw your dreams here."
  },
  {
   "page_no": 13,
   "word_count": 0,
   "text": ""
  },
  {
   "page_no": 14,
   "word_count": 0,
   "text": ""
  }
 ]
}