[
  {
    "page": 1,
    "image_url": "https://bookdash.github.io/bookdash-books/bathtub-safari/en/images/01.jpg",
    "text": "Bathtime is Jack’s favourite part of the day.\n‘I’ll be back in a few moments,’ says his mom. ‘Make sure to clean behind your ears.’"
  },
  {
    "page": 2,
    "image_url": "https://bookdash.github.io/bookdash-books/bathtub-safari/en/images/02.jpg",
    "text": "There’s a SWOOSH. And a swish of a tail.\nAnd then…"
  },
  {
    "page": 3,
    "image_url": "https://bookdash.github.io/bookdash-books/bathtub-safari/en/images/03.jpg",
    "text": "Jack’s bathtub safari begins!"
  },
  {
    "page": 4,
    "image_url": "https://bookdash.github.io/bookdash-books/bathtub-safari/en/images/04.jpg",
    "text": "Look at what’s coming!\nThere’s a twist and a turn..\nSomething’s growing…\nIt’s a…"
  },
  {
    "page": 5,
    "image_url": "https://bookdash.github.io/bookdash-books/bathtub-safari/en/images/05.jpg",
    "text": "TOOOT!"
  },
  {
    "page": 6,
    "image_url": "https://bookdash.github.io/bookdash-books/bathtub-safari/en/images/06.jpg",
    "text": "There’s a RUMBLE!\nUP\nUP\nIt’s going up\nand…"
  },
  {
    "page": 7,
    "image_url": "https://bookdash.github.io/bookdash-books/bathtub-safari/en/images/07.jpg",
    "text": "SPLASH!"
  },
  {
    "page": 8,
    "image_url": "https://bookdash.github.io/bookdash-books/bathtub-safari/en/images/08.jpg",
    "text": "There’s a SPLOSH. Something bubbles.\nIt’s time to…"
  },
  {
    "page": 9,
    "image_url": "https://bookdash.github.io/bookdash-books/bathtub-safari/en/images/09.jpg",
    "text": "AAAAAAH\nBut something’s lurking in the background…"
  },
  {
    "page": 10,
    "image_url": "https://bookdash.github.io/bookdash-books/bathtub-safari/en/images/10.jpg",
    "text": "ROAR"
  },
  {
    "page": 11,
    "image_url": "https://bookdash.github.io/bookdash-books/bathtub-safari/en/images/11.jpg",
    "text": "‘Time to get out. I hope you’re clean and ready for bed.’"
  },
  {
    "page": 12,
    "image_url": "https://bookdash.github.io/bookdash-books/bathtub-safari/en/images/12.jpg",
    "text": "Jack is fast asleep in bed surrounded by his toy animals."
  }
]